{
  "game": "queens",
  "n": 9,
  "regions": [
    [
      0,
      0,
      0,
      0,
      0,
      0,
      0,
      0,
      0
    ],
    [
      0,
      1,
      1,
      1,
      1,
      1,
      1,
      1,
      2
    ],
    [
      0,
      3,
      3,
      3,
      3,
      3,
      4,
      1,
      2
    ],
    [
      0,
      3,
      5,
      5,
      5,
      5,
      4,
      1,
      2
    ],
    [
      0,
      3,
      6,
      6,
      6,
      7,
      4,
      1,
      2
    ],
    [
      0,
      3,
      6,
      6,
      6,
      7,
      4,
      1,
      2
    ],
    [
      0,
      3,
      6,
      8,
      6,
      7,
      4,
      1,
      2
    ],
    [
      0,
      4,
      4,
      4,
      4,
      4,
      4,
      1,
      2
    ],
    [
      0,
      2,
      2,
      2,
      2,
      2,
      2,
      2,
      2
    ]
  ],
  "givens": {
    "queens": [],
    "blocked": []
  },
  "meta": {
    "source": "samimsu/queens-game-linkedin",
    "level_id": "49"
  }
}